dynamic_reader_aws/__init__.py
dynamic_reader_aws/main.py
dynamic_reader_aws-0.1.dist-info/METADATA
dynamic_reader_aws-0.1.dist-info/WHEEL
dynamic_reader_aws-0.1.dist-info/top_level.txt
dynamic_reader_aws-0.1.dist-info/RECORD
