Metadata-Version: 2.1
Name: dynamic_reader_aws
Version: 0.1
Summary: Directly use AWS Secrets Manager with Django settings.py
Author: Hunaid Vekariya
Author-email: itsmehunaid@gmail.com
Requires-Dist: boto3 >=1.18.0
